examples/hillipop_example.yaml
planck_2020_hillipop/EE.yaml
planck_2020_hillipop/TE.bibtex
planck_2020_hillipop/TE.yaml
planck_2020_hillipop/TT.bibtex
planck_2020_hillipop/TT.yaml
planck_2020_hillipop/TTTEEE.bibtex
planck_2020_hillipop/TTTEEE.yaml
planck_2020_hillipop/__init__.py
planck_2020_hillipop/_version.py
planck_2020_hillipop/foregrounds.py
planck_2020_hillipop/foregrounds.yaml
planck_2020_hillipop/hillipop.bibtex
planck_2020_hillipop/hillipop.py
planck_2020_hillipop/params_EE.yaml
planck_2020_hillipop/params_TE.yaml
planck_2020_hillipop/params_TT.yaml
planck_2020_hillipop/params_calib.yaml
planck_2020_hillipop/tools.py
planck_2020_hillipop/tests/test_hillipop.py
planck_2020_hillipop-4.2.2.dist-info/LICENSE
planck_2020_hillipop-4.2.2.dist-info/METADATA
planck_2020_hillipop-4.2.2.dist-info/WHEEL
planck_2020_hillipop-4.2.2.dist-info/top_level.txt
planck_2020_hillipop-4.2.2.dist-info/RECORD
